COPYRIGHT
MANIFEST.in
Makefile
README
setup.cfg
setup.py
test/__init__.py
test/__init__.pyc
test/test_compile.py
test/test_simple.py
test/__pycache__/test_compile.cpython-27-PYTEST.pyc
test/__pycache__/test_simple.cpython-27-PYTEST.pyc
tiddlywebplugins/__init__.py
tiddlywebplugins/virtualhosting.py
tiddlywebplugins.virtualhosting.egg-info/PKG-INFO
tiddlywebplugins.virtualhosting.egg-info/SOURCES.txt
tiddlywebplugins.virtualhosting.egg-info/dependency_links.txt
tiddlywebplugins.virtualhosting.egg-info/namespace_packages.txt
tiddlywebplugins.virtualhosting.egg-info/not-zip-safe
tiddlywebplugins.virtualhosting.egg-info/requires.txt
tiddlywebplugins.virtualhosting.egg-info/top_level.txt