Metadata-Version: 1.0
Name: tiddlywebplugins.virtualhosting
Version: 0.4
Summary: Enable virtualhosts from the same tiddlyweb server.
Home-page: http://pypi.python.org/pypi/tiddlywebplugins.virtualhosting
Author: Chris Dent
Author-email: cdent@peermore.com
License: BSD
Platform: Posix; MacOS X; Windows
